Metadata-Version: 2.1
Name: plwrap
Version: 0.1.0
Summary: Non ORM SQL Query runner
Home-page: https://github.com/xvzf/plwrap
Author: Matthias Riegler
Author-email: me@xvzf.tech
License: UNKNOWN
Platform: UNKNOWN
Classifier: Programming Language :: Python :: 3.6
Classifier: Programming Language :: Python :: 3.7
Classifier: Programming Language :: Python :: 3 :: Only
Classifier: Framework :: AsyncIO
Classifier: Topic :: Database
Classifier: License :: OSI Approved :: GNU General Public License v3 (GPLv3)
Requires-Python: >=3.6
